coinverter/__init__.py
coinverter/coinverter.py
coinverter-0.0.1.dist-info/METADATA
coinverter-0.0.1.dist-info/WHEEL
coinverter-0.0.1.dist-info/top_level.txt
coinverter-0.0.1.dist-info/RECORD
