Metadata-Version: 2.1
Name: coinverter
Version: 0.0.1
Summary: Convesor de moedas com base do Real Brasileiro
Home-page: https://github.com/PedroFelipe-G-Arruda/coinverter
Author: Pedro Arruda
Author-email: pedrofelipega@gmail.com
Requires-Python: >=3.8
Requires-Dist: requests==2.32.3
